{
  "notes": [
    {
      "details": "Emiliano's Birthday",
      "type": "event",
      "eventDate": "2023-03-17",
      "eventDay": "17",
      "eventMonth": "03",
      "eventYear": "2023",
      "dateCreated": "2023-2-11",
      "additionalNotes": null,
      "id": 2
    },
    {
      "details": "Carolyn's Birthday",
      "type": "event",
      "eventDate": "2023-02-23",
      "eventDay": "23",
      "eventMonth": "02",
      "eventYear": "2023",
      "dateCreated": "2023-2-11",
      "additionalNotes": null,
      "id": 3
    },
    {
      "details": "Corporate Org Chart",
      "type": "idea",
      "eventDate": null,
      "dateCreated": "2023-2-11",
      "additionalNotes": "lalalala",
      "id": 4
    },
    {
      "details": "Taxes",
      "type": "task",
      "eventDate": null,
      "dateCreated": "2023-2-13",
      "additionalNotes": null,
      "id": 7,
      "urgent": false,
      "important": true,
      "complete": false
    },
    {
      "details": "My Birthday",
      "type": "event",
      "eventDate": "2023-06-16",
      "eventDay": "16",
      "eventMonth": "06",
      "eventYear": "2023",
      "dateCreated": "2023-2-13",
      "additionalNotes": null,
      "id": 10
    },
    {
      "details": "Super Bowl",
      "type": "event",
      "eventDate": "2023-02-12",
      "eventDay": "12",
      "eventMonth": "02",
      "eventYear": "2023",
      "dateCreated": "2023-2-13",
      "additionalNotes": null,
      "id": 11
    },
    {
      "details": "Career video",
      "type": "task",
      "eventDate": null,
      "dateCreated": "2023-2-13",
      "additionalNotes": null,
      "id": 12,
      "urgent": false,
      "important": true,
      "complete": false
    },
    {
      "details": "Phase 2 lectures",
      "type": "task",
      "eventDate": null,
      "dateCreated": "2023-2-13",
      "additionalNotes": null,
      "id": 13,
      "urgent": false,
      "important": true,
      "complete": false
    },
    {
      "details": "Research Greek Mythology books ",
      "type": "idea",
      "eventDate": null,
      "dateCreated": "2023-2-13",
      "additionalNotes": null,
      "id": 14
    },
    {
      "details": "Megan's Birthday",
      "type": "event",
      "eventDate": "2023-08-19",
      "eventDay": "19",
      "eventMonth": "08",
      "eventYear": "2023",
      "dateCreated": "2023-2-13",
      "additionalNotes": null,
      "id": 15
    },
    {
      "details": "Pick Emiliano up from the airport (12pm)",
      "type": "event",
      "eventDate": "2023-02-14",
      "eventDay": "14",
      "eventMonth": "02",
      "eventYear": "2023",
      "dateCreated": "2023-2-13",
      "additionalNotes": null,
      "id": 16
    },
    {
      "details": "Call California Spine",
      "type": "task",
      "eventDate": null,
      "dateCreated": "2023-2-15",
      "additionalNotes": null,
      "id": 17,
      "urgent": false,
      "important": false,
      "complete": false
    },
    {
      "details": "Phase 2 Blog: context?",
      "type": "task",
      "eventDate": null,
      "dateCreated": "2023-2-15",
      "additionalNotes": null,
      "id": 18,
      "urgent": true,
      "important": true,
      "complete": false
    },
    {
      "details": "Blog: callback functions.",
      "type": "task",
      "eventDate": null,
      "dateCreated": "2023-2-15",
      "additionalNotes": null,
      "id": 19,
      "urgent": false,
      "important": false,
      "complete": false
    },
    {
      "details": "Then thousand flowers in the spring, the moon in autumn. A cool breeze in summer, snow in winter. If your mind isn't clouded be unnecessary things, this is the best season of your life. - Wu Min ",
      "type": "idea",
      "eventDate": null,
      "dateCreated": "2023-2-14",
      "additionalNotes": null,
      "id": 21
    },
    {
      "details": "Astian + Josh gift and note",
      "type": "task",
      "eventDate": null,
      "dateCreated": "2023-2-15",
      "additionalNotes": null,
      "id": 22,
      "urgent": true,
      "important": true,
      "complete": false
    },
    {
      "details": "Stick to your knitting ",
      "type": "idea",
      "eventDate": null,
      "dateCreated": "2023-2-14",
      "additionalNotes": null,
      "id": 23
    },
    {
      "details": "Buy ingredients for todd",
      "type": "task",
      "eventDate": null,
      "dateCreated": "2023-02-16",
      "additionalNotes": null,
      "urgent": true,
      "important": true,
      "complete": false,
      "id": 24
    },
    {
      "details": "Valentines Day",
      "type": "event",
      "eventDate": "2023-02-14",
      "eventDay": "14",
      "eventMonth": "02",
      "eventYear": "2023",
      "dateCreated": "2023-02-16",
      "additionalNotes": null,
      "urgent": false,
      "important": false,
      "complete": false,
      "id": 25
    },
    {
      "details": "Hang with Jackie + Zan",
      "type": "event",
      "eventDate": "2023-02-18",
      "eventDay": "18",
      "eventMonth": "02",
      "eventYear": "2023",
      "dateCreated": "2023-02-16",
      "additionalNotes": null,
      "urgent": false,
      "important": false,
      "complete": false,
      "id": 26
    },
    {
      "details": "Dinner with Emiliano",
      "type": "event",
      "eventDate": "2023-02-17",
      "eventDay": "17",
      "eventMonth": "02",
      "eventYear": "2023",
      "dateCreated": "2023-02-16",
      "additionalNotes": null,
      "urgent": false,
      "important": false,
      "complete": false,
      "id": 27
    },
    {
      "details": "Astian on vacation",
      "type": "event",
      "eventDate": "2023-02-19",
      "eventDay": "19",
      "eventMonth": "02",
      "eventYear": "2023",
      "dateCreated": "2023-02-16",
      "additionalNotes": null,
      "urgent": false,
      "important": false,
      "complete": false,
      "id": 28
    }
  ],
  "months": {}
}